terminal_control_mcp/__init__.py
terminal_control_mcp/config.py
terminal_control_mcp/interaction_logger.py
terminal_control_mcp/interactive_session.py
terminal_control_mcp/main.py
terminal_control_mcp/models.py
terminal_control_mcp/security.py
terminal_control_mcp/session_manager.py
terminal_control_mcp/terminal_utils.py
terminal_control_mcp/utils.py
terminal_control_mcp/web_server.py
terminal_control_mcp/static/css/main.css
terminal_control_mcp/static/css/session.css
terminal_control_mcp/static/js/keyboard-shortcuts.js
terminal_control_mcp/static/js/overview.js
terminal_control_mcp/static/js/session.js
terminal_control_mcp/templates/index.html
terminal_control_mcp/templates/session.html
terminal_control_mcp-1.0.3.dist-info/licenses/LICENSE
terminal_control_mcp-1.0.3.dist-info/METADATA
terminal_control_mcp-1.0.3.dist-info/WHEEL
terminal_control_mcp-1.0.3.dist-info/entry_points.txt
terminal_control_mcp-1.0.3.dist-info/top_level.txt
terminal_control_mcp-1.0.3.dist-info/RECORD
