Metadata-Version: 2.4
Name: terminal-control-mcp
Version: 1.0.3
Summary: Terminal Control MCP Server
Author-email: Mark Wernsdorfer <wernsdorfer@gmail.com>
License: MIT
Project-URL: Homepage, https://github.com/wehnsdaefflae/terminal-control-mcp
Project-URL: Documentation, https://github.com/wehnsdaefflae/terminal-control-mcp/blob/main/README.md
Project-URL: Repository, https://github.com/wehnsdaefflae/terminal-control-mcp
Project-URL: Issues, https://github.com/wehnsdaefflae/terminal-control-mcp/issues
Keywords: mcp,terminal,control,debugging,ssh,database
Classifier: Development Status :: 4 - Beta
Classifier: Intended Audience :: Developers
Classifier: License :: OSI Approved :: MIT License
Classifier: Programming Language :: Python :: 3
Classifier: Programming Language :: Python :: 3.9
Classifier: Programming Language :: Python :: 3.10
Classifier: Programming Language :: Python :: 3.11
Classifier: Programming Language :: Python :: 3.12
Classifier: Programming Language :: Python :: 3.13
Classifier: Topic :: Software Development :: Libraries :: Python Modules
Classifier: Topic :: System :: Systems Administration
Classifier: Topic :: Software Development :: Debuggers
Requires-Python: >=3.9
License-File: LICENSE
Requires-Dist: mcp>=1.0.0
Requires-Dist: typing-extensions>=4.0.0
Requires-Dist: pydantic>=2.11.7
Requires-Dist: fastapi>=0.104.0
Requires-Dist: uvicorn>=0.24.0
Requires-Dist: websockets>=12.0
Requires-Dist: jinja2>=3.1.0
Requires-Dist: rich>=13.0.0
Requires-Dist: libtmux>=0.15.0
Requires-Dist: tomli>=1.2.0; python_version < "3.11"
Provides-Extra: dev
Requires-Dist: mcp[cli]>=1.0.0; extra == "dev"
Requires-Dist: black>=22.0.0; extra == "dev"
Requires-Dist: isort>=5.10.0; extra == "dev"
Requires-Dist: mypy>=0.950; extra == "dev"
Requires-Dist: ruff>=0.1.0; extra == "dev"
Requires-Dist: pytest>=7.0.0; extra == "dev"
Requires-Dist: pytest-asyncio>=0.21.0; extra == "dev"
Requires-Dist: vulture>=2.3; extra == "dev"
Requires-Dist: twine>=6.1.0; extra == "dev"
Requires-Dist: build>=1.2.2.post1; extra == "dev"
Dynamic: license-file
